{
  "id": "8-1",
  "title": "プロジェクト・サービスマネジメント",
  "cards": [
    { "front": "プロジェクト憲章", "back": "プロジェクトの目的・目標・責任者の権限などを定めた公式文書で、プロジェクト開始を正式に認可する。ステークホルダの特定や合意形成の起点にもなる。" },
    { "front": "WBS", "back": "プロジェクトの成果物を達成に必要な作業に段階的に分解した階層構造図。作業単位を明確化し、担当・スケジュール・コストの管理単位とする。" },
    { "front": "PERT", "back": "作業の順序関係を図示し、各経路の所要日数から最短完了日数（クリティカルパス）を求める工程管理図法。日程短縮の余地がある作業の把握に使う。" },
    { "front": "プロジェクトマネジメントの知識エリア", "back": "PMBOKが定める、統合・スコープ・スケジュール・コスト・品質・資源・コミュニケーション・リスク・調達・ステークホルダの10領域。管理の全体像を示す地図。" },
    { "front": "SLA", "back": "サービス提供者と利用者間で、可用性や応答時間など提供品質の水準を数値目標として取り決めた合意文書。合意違反時の対応も定める。" },
    { "front": "サービスレベル目標", "back": "SLAに定める個々の品質項目の具体的な数値目標（稼働率99.9％など）。契約文書であるSLAに対し、その中の測定可能な目標値を指す。", "frontInfo": "SLO（Service Level Objective）と略される" },
    { "front": "インシデント管理（ITSM）", "back": "ITサービスの中断や品質低下を検知し、暫定対応で迅速に復旧させるプロセス。セキュリティ事故そのものへの対応とは目的が異なる。", "frontInfo": "ITSMのプロセスの一つ。情報セキュリティインシデントハンドリングとは区別される" },
    { "front": "問題管理（既知の誤り・根本原因）", "back": "インシデントの根本原因を分析し、原因が判明した未解決の問題を既知の誤りとして暫定回避策（ワークアラウンド）とともに記録するITSMプロセス。" },
    { "front": "エスカレーション", "back": "自分の権限や能力で対応できない問題を、上位者や専門部署に引き継ぐこと。機能的なものと階層的（管理的）なものに大別される。" },
    { "front": "構成管理・構成品目（CI）", "back": "ITサービスを構成するハードウェアや文書などの要素を特定し、関係性や状態をCMDBで記録・維持管理する活動。変更管理の基礎情報となる。", "frontInfo": "管理対象の個々の要素＝構成品目（CI）" },
    { "front": "変更管理", "back": "ITサービスへの変更を評価・承認・実施・レビューする統制されたプロセス。影響評価を経ずに変更を加えることによる障害発生を防ぐ。" },
    { "front": "RTO・RPO・RLO", "back": "業務再開までの目標時間、復旧時に許容できるデータ損失の時点、復旧時に確保すべき業務水準を示す3つの指標。BCP策定で用いる。", "frontInfo": "目標時間＝RTO、データ損失時点＝RPO、業務水準＝RLO" },
    { "front": "コールドスタンバイ／ホットスタンバイ", "back": "予備システムの待機形態。平常時は停止しておき障害時に起動するため復旧に時間を要するものと、常時稼働・同期させ即座に切替えられるものがある。", "frontInfo": "停止待機＝コールド、常時稼働＝ホット" }
  ]
}
